{
    "name": "flowmcp-schemas",
    "version": "1.0.0",
    "description": "Official FlowMCP community schemas - Complete Collection",
    "schemaSpec": "1.2.0",
    "baseDir": "schemas/v1.2.0",
    "registryType": "all",
    "schemas": [
        {
            "namespace": "aave",
            "file": "aave/aave.mjs",
            "name": "AAVE Protocol API",
            "requiredServerParams": [
                "THEGRAPH_API_KEY"
            ],
            "requiredModules": []
        },
        {
            "namespace": "alternative",
            "file": "alternative-me/fearAndGreed.mjs",
            "name": "FearGreedIndex",
            "requiredServerParams": [],
            "requiredModules": []
        },
        {
            "namespace": "berlinevents",
            "file": "berlin-de/events.mjs",
            "name": "Berlin Events API",
            "requiredServerParams": [],
            "requiredModules": []
        },
        {
            "namespace": "berlinfunds",
            "file": "berlin-de/funds.mjs",
            "name": "Berlin Funds API",
            "requiredServerParams": [],
            "requiredModules": []
        },
        {
            "namespace": "berlinvhs",
            "file": "berlin-de/vhs.mjs",
            "name": "Berlin VHS API",
            "requiredServerParams": [],
            "requiredModules": []
        },
        {
            "namespace": "berlinwfs",
            "file": "berlin-de/wfs-locations.mjs",
            "name": "Berlin WFS Locations API",
            "requiredServerParams": [],
            "requiredModules": []
        },
        {
            "namespace": "bicscan",
            "file": "bicscan/bicscan.mjs",
            "name": "BICScan API",
            "requiredServerParams": [
                "BICSCAN_API_KEY"
            ],
            "requiredModules": []
        },
        {
            "namespace": "bitget",
            "file": "bitget/bitget.mjs",
            "name": "Bitget Crypto Tools",
            "requiredServerParams": [],
            "requiredModules": []
        },
        {
            "namespace": "blockberry",
            "file": "blockberry-one/mina-mainnet.mjs",
            "name": "Blockberry Mina Mainnet API",
            "requiredServerParams": [
                "BLOCKBERRY_API_KEY"
            ],
            "requiredModules": []
        },
        {
            "namespace": "blocknative",
            "file": "blocknative/gasprice.mjs",
            "name": "Gas Price Estimator",
            "requiredServerParams": [
                "BLOCKNATIVE_API_KEY"
            ],
            "requiredModules": []
        },
        {
            "namespace": "bridgeRates",
            "file": "bridgerates/bridgerates.mjs",
            "name": "LiFi Bridge API",
            "requiredServerParams": [],
            "requiredModules": []
        },
        {
            "namespace": "bscscan",
            "file": "bscscan/getContractBinance.mjs",
            "name": "BSC Scan",
            "requiredServerParams": [
                "BSCSCAN_API_KEY"
            ],
            "requiredModules": []
        },
        {
            "namespace": "chainlink",
            "file": "chainlink/getLatestPrices.mjs",
            "name": "ExampleName",
            "requiredServerParams": [
                "INFURA_API_KEY"
            ],
            "requiredModules": [
                {
                    "name": "ethers",
                    "version": "^6.13.7"
                }
            ]
        },
        {
            "namespace": "chainlinkMulticall",
            "file": "chainlink/getLatestPricesMulticall.mjs",
            "name": "Multicall Latest Prices",
            "requiredServerParams": [
                "INFURA_API_KEY"
            ],
            "requiredModules": [
                {
                    "name": "ethers",
                    "version": "^6.13.7"
                }
            ]
        },
        {
            "namespace": "chainlist",
            "file": "chainlist/chainlist.mjs",
            "name": "Chainlist Tools",
            "requiredServerParams": [],
            "requiredModules": []
        },
        {
            "namespace": "chartImg",
            "file": "chart-img-com/tradingview-charts.mjs",
            "name": "Chart Image API",
            "requiredServerParams": [
                "CHART_IMG_API_KEY"
            ],
            "requiredModules": []
        },
        {
            "namespace": "coincap",
            "file": "coincap/assets.mjs",
            "name": "AssetsAPI",
            "requiredServerParams": [
                "COINCAP_API_KEY"
            ],
            "requiredModules": []
        },
        {
            "namespace": "coincap",
            "file": "coincap/exchanges.mjs",
            "name": "CoinCapExchanges",
            "requiredServerParams": [
                "COINCAP_API_KEY"
            ],
            "requiredModules": []
        },
        {
            "namespace": "coincap",
            "file": "coincap/markets.mjs",
            "name": "CoinCapMarkets",
            "requiredServerParams": [
                "COINCAP_API_KEY"
            ],
            "requiredModules": []
        },
        {
            "namespace": "coincap",
            "file": "coincap/rates.mjs",
            "name": "CoinCapRates",
            "requiredServerParams": [
                "COINCAP_API_KEY"
            ],
            "requiredModules": []
        },
        {
            "namespace": "coingecko",
            "file": "coingecko-com/coingecko-stablecoins.mjs",
            "name": "CoinGecko Stablecoins API",
            "requiredServerParams": [],
            "requiredModules": []
        },
        {
            "namespace": "coingecko",
            "file": "coingecko-com/coins.mjs",
            "name": "CoinGeckoCoins",
            "requiredServerParams": [],
            "requiredModules": []
        },
        {
            "namespace": "coingecko",
            "file": "coingecko-com/derivatives.mjs",
            "name": "CoinGeckoDerivatives",
            "requiredServerParams": [],
            "requiredModules": []
        },
        {
            "namespace": "coingecko",
            "file": "coingecko-com/exchanges.mjs",
            "name": "CoinGeckoExchanges",
            "requiredServerParams": [],
            "requiredModules": []
        },
        {
            "namespace": "coingecko",
            "file": "coingecko-com/getCategories.mjs",
            "name": "CoinGeckoCategories",
            "requiredServerParams": [],
            "requiredModules": []
        },
        {
            "namespace": "coingecko",
            "file": "coingecko-com/global.mjs",
            "name": "CoinGeckoGlobal",
            "requiredServerParams": [],
            "requiredModules": []
        },
        {
            "namespace": "coingecko",
            "file": "coingecko-com/simplePrice.mjs",
            "name": "CoinGeckoSimplePrice",
            "requiredServerParams": [],
            "requiredModules": []
        },
        {
            "namespace": "coingecko",
            "file": "coingecko-com/trending.mjs",
            "name": "CoinGeckoTrending",
            "requiredServerParams": [],
            "requiredModules": []
        },
        {
            "namespace": "coinmarketcap",
            "file": "coinmarketcap-com/category.mjs",
            "name": "CoinMarketCap Categories",
            "requiredServerParams": [
                "CMC_API_KEY"
            ],
            "requiredModules": []
        },
        {
            "namespace": "coinmarketcap",
            "file": "coinmarketcap-com/cmc-index.mjs",
            "name": "CoinMarketCap100",
            "requiredServerParams": [
                "CMC_API_KEY"
            ],
            "requiredModules": []
        },
        {
            "namespace": "coinmarketcap",
            "file": "coinmarketcap-com/fear-and-greed.mjs",
            "name": "CMCCryptoFearAndGreed",
            "requiredServerParams": [
                "CMC_API_KEY"
            ],
            "requiredModules": []
        },
        {
            "namespace": "coinmarketcap",
            "file": "coinmarketcap-com/listings.mjs",
            "name": "CoinMarketCapListingsLatest",
            "requiredServerParams": [
                "CMC_API_KEY"
            ],
            "requiredModules": []
        },
        {
            "namespace": "cointelegraph",
            "file": "cointelegraph/getLatestNews.mjs",
            "name": "CointelegraphRSS",
            "requiredServerParams": [],
            "requiredModules": []
        },
        {
            "namespace": "context7",
            "file": "context-7/getDocumentation.mjs",
            "name": "Context7 Library Docs",
            "requiredServerParams": [],
            "requiredModules": []
        },
        {
            "namespace": "cryptodata",
            "file": "coinstats/mixed.mjs",
            "name": "Get Coins",
            "requiredServerParams": [
                "COINSTATS_API_KEY"
            ],
            "requiredModules": []
        },
        {
            "namespace": "cryptoOrderbook",
            "file": "ccxt/orderbook.mjs",
            "name": "Crypto Order Book Metrics",
            "requiredServerParams": [],
            "requiredModules": [
                {
                    "name": "ccxt",
                    "version": "^4.5.0"
                }
            ]
        },
        {
            "namespace": "cryptopanic",
            "file": "cryptopanic/getNews.mjs",
            "name": "CryptoPanic",
            "requiredServerParams": [
                "CRYPTOPANIC_API_KEY"
            ],
            "requiredModules": []
        },
        {
            "namespace": "cryptowizards",
            "file": "cryptowizards-net/analytics.mjs",
            "name": "CryptoWizards Analytics API",
            "requiredServerParams": [
                "CRYPTOWIZARDS_API_KEY"
            ],
            "requiredModules": []
        },
        {
            "namespace": "defillama",
            "file": "defilama/api.mjs",
            "name": "DeFi Llama MCP",
            "requiredServerParams": [],
            "requiredModules": []
        },
        {
            "namespace": "defillama",
            "file": "defilama/coins.mjs",
            "name": "DeFi Llama Token Prices",
            "requiredServerParams": [],
            "requiredModules": []
        },
        {
            "namespace": "defillama",
            "file": "defilama/yields.mjs",
            "name": "DeFi Llama Liquidity Pools",
            "requiredServerParams": [],
            "requiredModules": []
        },
        {
            "namespace": "dexscreener",
            "file": "dexscreener-com/boosted.mjs",
            "name": "dexscreener-boosted",
            "requiredServerParams": [],
            "requiredModules": []
        },
        {
            "namespace": "dexscreener",
            "file": "dexscreener-com/pairs.mjs",
            "name": "Dexscreener Pairs",
            "requiredServerParams": [],
            "requiredModules": []
        },
        {
            "namespace": "dexscreener",
            "file": "dexscreener-com/tokenInfo.mjs",
            "name": "dexscreener-tokeninfo",
            "requiredServerParams": [],
            "requiredModules": []
        },
        {
            "namespace": "dexscreener",
            "file": "dexscreener-com/tokenpairs.mjs",
            "name": "DexScreener Token Pairs API",
            "requiredServerParams": [],
            "requiredModules": []
        },
        {
            "namespace": "duneAnalytics",
            "file": "dune-analytics/farcaster.mjs",
            "name": "FarcasterTrends",
            "requiredServerParams": [
                "DUNE_API_KEY"
            ],
            "requiredModules": []
        },
        {
            "namespace": "duneAnalytics",
            "file": "dune-analytics/getResults.mjs",
            "name": "DuneAnalytics",
            "requiredServerParams": [
                "DUNE_API_KEY"
            ],
            "requiredModules": []
        },
        {
            "namespace": "duneAnalytics",
            "file": "dune-analytics/trendingContracts.mjs",
            "name": "DexAndContracts",
            "requiredServerParams": [
                "DUNE_API_KEY"
            ],
            "requiredModules": []
        },
        {
            "namespace": "ens",
            "file": "ens/ens-resolution.mjs",
            "name": "ENS & EVM Name Resolution",
            "requiredServerParams": [
                "INFURA_API_KEY"
            ],
            "requiredModules": [
                {
                    "name": "ethers",
                    "version": "^6.13.7"
                }
            ]
        },
        {
            "namespace": "epo",
            "file": "epo-org/patent-search.mjs",
            "name": "European Patent Office RSS Search",
            "requiredServerParams": [],
            "requiredModules": []
        },
        {
            "namespace": "etherscan",
            "file": "etherscan/getContractEthereum.mjs",
            "name": "Etherscan",
            "requiredServerParams": [
                "ETHERSCAN_API_KEY"
            ],
            "requiredModules": []
        },
        {
            "namespace": "etherscan",
            "file": "etherscan/getContractMultichain.mjs",
            "name": "SmartContractExplorer",
            "requiredServerParams": [
                "ETHERSCAN_API_KEY"
            ],
            "requiredModules": []
        },
        {
            "namespace": "etherscan",
            "file": "etherscan/getGaspriceMultichain.mjs",
            "name": "SmartContractExplorer",
            "requiredServerParams": [
                "ETHERSCAN_API_KEY"
            ],
            "requiredModules": []
        },
        {
            "namespace": "ethscriptions",
            "file": "ethscriptions-com/ethscriptions-api.mjs",
            "name": "Ethscriptions API V2",
            "requiredServerParams": [],
            "requiredModules": []
        },
        {
            "namespace": "goldskyLilNouns",
            "file": "goldsky-nouns/lil-nouns.mjs",
            "name": "Lil Nouns Subgraph",
            "requiredServerParams": [],
            "requiredModules": []
        },
        {
            "namespace": "goldskyNouns",
            "file": "goldsky-nouns/goldsky-nouns.mjs",
            "name": "Nouns DAO Subgraph",
            "requiredServerParams": [],
            "requiredModules": []
        },
        {
            "namespace": "goldskyNouns",
            "file": "goldsky-nouns/nouns.mjs",
            "name": "Nouns DAO Subgraph",
            "requiredServerParams": [],
            "requiredModules": []
        },
        {
            "namespace": "honeypot",
            "file": "honeypot/honeypot.mjs",
            "name": "Honeypot Detector",
            "requiredServerParams": [],
            "requiredModules": []
        },
        {
            "namespace": "indicatorts",
            "file": "indicators/indicatorts-schema.mjs",
            "name": "OHLCV Indicators",
            "requiredServerParams": [],
            "requiredModules": [
                {
                    "name": "indicatorts",
                    "version": "^2.2.2"
                }
            ]
        },
        {
            "namespace": "jupiter",
            "file": "jupiter/jupiter-all.mjs",
            "name": "Jupiter Token Price Checker",
            "requiredServerParams": [],
            "requiredModules": []
        },
        {
            "namespace": "llama",
            "file": "llama-fi/getPools.mjs",
            "name": "DeFiYieldsServer",
            "requiredServerParams": [],
            "requiredModules": []
        },
        {
            "namespace": "luksoNetwork",
            "file": "erc725/universalProfile.mjs",
            "name": "ERC725UniversalProfile",
            "requiredServerParams": [],
            "requiredModules": [
                {
                    "name": "@erc725/erc725.js",
                    "version": "^0.27.2"
                }
            ]
        },
        {
            "namespace": "luksoNetwork",
            "file": "lukso-network/address.mjs",
            "name": "LUKSO BlockScout Addresses",
            "requiredServerParams": [],
            "requiredModules": []
        },
        {
            "namespace": "luksoNetwork",
            "file": "lukso-network/blocks.mjs",
            "name": "LUKSO BlockScout Blocks",
            "requiredServerParams": [],
            "requiredModules": []
        },
        {
            "namespace": "luksoNetwork",
            "file": "lukso-network/graphql.mjs",
            "name": "LuksoMainnetSubgraph",
            "requiredServerParams": [],
            "requiredModules": []
        },
        {
            "namespace": "luksoNetwork",
            "file": "lukso-network/internal.mjs",
            "name": "LUKSO BlockScout Meta",
            "requiredServerParams": [],
            "requiredModules": []
        },
        {
            "namespace": "luksoNetwork",
            "file": "lukso-network/nfts.mjs",
            "name": "LUKSO BlockScout NFTs",
            "requiredServerParams": [],
            "requiredModules": []
        },
        {
            "namespace": "luksoNetwork",
            "file": "lukso-network/search.mjs",
            "name": "LUKSO BlockScout Search",
            "requiredServerParams": [],
            "requiredModules": []
        },
        {
            "namespace": "luksoNetwork",
            "file": "lukso-network/sourceCode.mjs",
            "name": "Contract",
            "requiredServerParams": [],
            "requiredModules": []
        },
        {
            "namespace": "luksoNetwork",
            "file": "lukso-network/stats.mjs",
            "name": "LUKSO BlockScout Statistics",
            "requiredServerParams": [],
            "requiredModules": []
        },
        {
            "namespace": "luksoNetwork",
            "file": "lukso-network/tokens.mjs",
            "name": "LUKSO BlockScout Tokens",
            "requiredServerParams": [],
            "requiredModules": []
        },
        {
            "namespace": "luksoNetwork",
            "file": "lukso-network/transactions.mjs",
            "name": "LUKSO BlockScout Transactions",
            "requiredServerParams": [],
            "requiredModules": []
        },
        {
            "namespace": "medium",
            "file": "medium-com/rss-feeds.mjs",
            "name": "Medium RSS Feeds",
            "requiredServerParams": [],
            "requiredModules": []
        },
        {
            "namespace": "memoryLol",
            "file": "memory-lol/twitterNameChanges.mjs",
            "name": "TwitterUsernameChanges",
            "requiredServerParams": [],
            "requiredModules": []
        },
        {
            "namespace": "minascanDevnet",
            "file": "minascan-io/mina-devnet.mjs",
            "name": "MinaScan Devnet GraphQL API",
            "requiredServerParams": [],
            "requiredModules": []
        },
        {
            "namespace": "minascanMainnet",
            "file": "minascan-io/mina-mainnet.mjs",
            "name": "MinaScan Mainnet GraphQL API",
            "requiredServerParams": [],
            "requiredModules": []
        },
        {
            "namespace": "moralis",
            "file": "moralis-com/eth/blockchainApi.mjs",
            "name": "Moralis blockchainApi API",
            "requiredServerParams": [
                "MORALIS_API_KEY"
            ],
            "requiredModules": []
        },
        {
            "namespace": "moralis",
            "file": "moralis-com/eth/defiApi.mjs",
            "name": "Moralis defiApi API",
            "requiredServerParams": [
                "MORALIS_API_KEY"
            ],
            "requiredModules": []
        },
        {
            "namespace": "moralis",
            "file": "moralis-com/eth/entity.mjs",
            "name": "Moralis entity API",
            "requiredServerParams": [
                "MORALIS_API_KEY"
            ],
            "requiredModules": []
        },
        {
            "namespace": "moralis",
            "file": "moralis-com/eth/nftApi.mjs",
            "name": "Moralis nftApi API",
            "requiredServerParams": [
                "MORALIS_API_KEY"
            ],
            "requiredModules": []
        },
        {
            "namespace": "moralis",
            "file": "moralis-com/eth/priceApi.mjs",
            "name": "Moralis priceApi API",
            "requiredServerParams": [
                "MORALIS_API_KEY"
            ],
            "requiredModules": []
        },
        {
            "namespace": "moralis",
            "file": "moralis-com/eth/tokenApi.mjs",
            "name": "Moralis tokenApi API",
            "requiredServerParams": [
                "MORALIS_API_KEY"
            ],
            "requiredModules": []
        },
        {
            "namespace": "moralis",
            "file": "moralis-com/eth/utils.mjs",
            "name": "Moralis utils API",
            "requiredServerParams": [
                "MORALIS_API_KEY"
            ],
            "requiredModules": []
        },
        {
            "namespace": "moralis",
            "file": "moralis-com/eth/walletApi.mjs",
            "name": "Moralis walletApi API",
            "requiredServerParams": [
                "MORALIS_API_KEY"
            ],
            "requiredModules": []
        },
        {
            "namespace": "newsapi",
            "file": "newsapi-org/news.mjs",
            "name": "NewsAPI.org",
            "requiredServerParams": [
                "NEWSAPI_API_KEY"
            ],
            "requiredModules": []
        },
        {
            "namespace": "newsdata",
            "file": "newsdata-io/getNews.mjs",
            "name": "CryptoNews",
            "requiredServerParams": [
                "NEWSDATA_API_KEY"
            ],
            "requiredModules": []
        },
        {
            "namespace": "ohlcv",
            "file": "ohlcv/olhcv-moralis-evm.mjs",
            "name": "Moralis Recursive OHLCV EVM and Ethereum",
            "requiredServerParams": [
                "MORALIS_API_KEY"
            ],
            "requiredModules": [
                {
                    "name": "axios",
                    "version": "^1.11.0"
                },
                {
                    "name": "moment",
                    "version": "^2.30.1"
                }
            ]
        },
        {
            "namespace": "ohlcv",
            "file": "ohlcv/olhcv-moralis-solana.mjs",
            "name": "Moralis Recursive OHLCV Solana",
            "requiredServerParams": [
                "MORALIS_API_KEY"
            ],
            "requiredModules": [
                {
                    "name": "axios",
                    "version": "^1.11.0"
                },
                {
                    "name": "moment",
                    "version": "^2.30.1"
                }
            ]
        },
        {
            "namespace": "ohlcv",
            "file": "ohlcv/olhcv-solana-tracker.mjs",
            "name": "Solana Tracker OHLCV for Solana",
            "requiredServerParams": [
                "SOLANA_TRACKER_API_KEY"
            ],
            "requiredModules": [
                {
                    "name": "moment",
                    "version": "^2.30.1"
                }
            ]
        },
        {
            "namespace": "passportOnchain",
            "file": "passport-xyz/onchain-data.mjs",
            "name": "Passport On-Chain Data API",
            "requiredServerParams": [
                "ETHEREUM_MAINNET_ALCHEMY_HTTP",
                "ARBITRUM_MAINNET_ALCHEMY_HTTP"
            ],
            "requiredModules": [
                {
                    "name": "ethers",
                    "version": "^6.13.7"
                }
            ]
        },
        {
            "namespace": "pinata",
            "file": "pinata/read.mjs",
            "name": "Pinata IPFS Read MCP Interface",
            "requiredServerParams": [],
            "requiredModules": []
        },
        {
            "namespace": "pinata",
            "file": "pinata/write.mjs",
            "name": "Pinata SDK Upload",
            "requiredServerParams": [
                "PINATA_JWT",
                "PINATA_GATEWAY"
            ],
            "requiredModules": [
                {
                    "name": "pinata",
                    "version": "^2.4.8"
                }
            ]
        },
        {
            "namespace": "poap",
            "file": "poap/graphql.mjs",
            "name": "POAP GraphQL",
            "requiredServerParams": [],
            "requiredModules": []
        },
        {
            "namespace": "polymarket",
            "file": "polymarket/marketInfo.mjs",
            "name": "Polymarket Predictions",
            "requiredServerParams": [],
            "requiredModules": []
        },
        {
            "namespace": "polymarket",
            "file": "polymarket/searchBySlug.mjs",
            "name": "Fed Rate Cuts 2025",
            "requiredServerParams": [],
            "requiredModules": []
        },
        {
            "namespace": "profilejump",
            "file": "erc725/profileJump.mjs",
            "name": "ProfileJump",
            "requiredServerParams": [],
            "requiredModules": []
        },
        {
            "namespace": "redditScanner",
            "file": "reddit/getTokenMentions.mjs",
            "name": "Reddit Token Mention Search",
            "requiredServerParams": [],
            "requiredModules": []
        },
        {
            "namespace": "santiment",
            "file": "santiment-net/schema.mjs",
            "name": "SantimentAnalytics",
            "requiredServerParams": [
                "SANTIMENT_API_KEY"
            ],
            "requiredModules": []
        },
        {
            "namespace": "simdune",
            "file": "simdune/activityEVM.mjs",
            "name": "Sim by Dune - Activity Feed",
            "requiredServerParams": [
                "DUNE_SIM_API_KEY"
            ],
            "requiredModules": [
                {
                    "name": "indicatorts",
                    "version": "^2.2.2"
                }
            ]
        },
        {
            "namespace": "simdune",
            "file": "simdune/balancesEVM.mjs",
            "name": "Sim by Dune - Token Balances",
            "requiredServerParams": [
                "DUNE_SIM_API_KEY"
            ],
            "requiredModules": []
        },
        {
            "namespace": "simdune",
            "file": "simdune/balancesSVM.mjs",
            "name": "Sim by Dune - SVM Token Balances",
            "requiredServerParams": [
                "DUNE_SIM_API_KEY"
            ],
            "requiredModules": []
        },
        {
            "namespace": "simdune",
            "file": "simdune/collectiblesEVM.mjs",
            "name": "Sim by Dune - NFT Collectibles",
            "requiredServerParams": [
                "DUNE_SIM_API_KEY"
            ],
            "requiredModules": []
        },
        {
            "namespace": "simdune",
            "file": "simdune/tokenHoldersEVM.mjs",
            "name": "Sim by Dune - Token Holders",
            "requiredServerParams": [
                "DUNE_SIM_API_KEY"
            ],
            "requiredModules": []
        },
        {
            "namespace": "simdune",
            "file": "simdune/tokenInfoEVM.mjs",
            "name": "Sim by Dune - Token Info",
            "requiredServerParams": [
                "DUNE_SIM_API_KEY"
            ],
            "requiredModules": []
        },
        {
            "namespace": "simdune",
            "file": "simdune/transactionsEVM.mjs",
            "name": "Sim by Dune - Transactions",
            "requiredServerParams": [
                "DUNE_SIM_API_KEY"
            ],
            "requiredModules": []
        },
        {
            "namespace": "simdune",
            "file": "simdune/transactionsSVM.mjs",
            "name": "Sim by Dune - SVM Transactions",
            "requiredServerParams": [
                "DUNE_SIM_API_KEY"
            ],
            "requiredModules": []
        },
        {
            "namespace": "snapshot",
            "file": "snapshot/snapshot.mjs",
            "name": "Snapshot DAO Proposals",
            "requiredServerParams": [],
            "requiredModules": []
        },
        {
            "namespace": "solscan",
            "file": "solscan-io/getChainInfo.mjs",
            "name": "SolscanChainInfo",
            "requiredServerParams": [
                "SOLSCAN_API_KEY"
            ],
            "requiredModules": []
        },
        {
            "namespace": "solsniffer",
            "file": "solsniffer-com/analysis.mjs",
            "name": "SolSniffer",
            "requiredServerParams": [
                "SOLSNIFFER_API_KEY"
            ],
            "requiredModules": []
        },
        {
            "namespace": "spaceid",
            "file": "spaceid/spaceid.mjs",
            "name": "SPACE ID Web3 Name API",
            "requiredServerParams": [],
            "requiredModules": []
        },
        {
            "namespace": "stolpersteineBerl",
            "file": "stolpersteine-berlin/memorial-stones.mjs",
            "name": "Stolpersteine Berlin API",
            "requiredServerParams": [],
            "requiredModules": []
        },
        {
            "namespace": "swaggerhub",
            "file": "swaggerhub-com/api-registry.mjs",
            "name": "SwaggerHub API",
            "requiredServerParams": [],
            "requiredModules": []
        },
        {
            "namespace": "thegraph",
            "file": "thegraph/getNewUniswapPools.mjs",
            "name": "UniswapPools",
            "requiredServerParams": [
                "THEGRAPH_API_KEY"
            ],
            "requiredModules": []
        },
        {
            "namespace": "thegraph",
            "file": "thegraph/getSchema.mjs",
            "name": "TheGraphSubgraphTools",
            "requiredServerParams": [
                "THEGRAPH_API_KEY"
            ],
            "requiredModules": []
        },
        {
            "namespace": "twitter",
            "file": "twitter/search.mjs",
            "name": "Twitter Recent Search",
            "requiredServerParams": [
                "TWITTER_BEARER_TOKEN"
            ],
            "requiredModules": []
        },
        {
            "namespace": "uniswap",
            "file": "uniswap-pools/uniswap-pool-explorer.mjs",
            "name": "Uniswap Pool Explorer",
            "requiredServerParams": [
                "THEGRAPH_API_KEY"
            ],
            "requiredModules": []
        },
        {
            "namespace": "uniswap",
            "file": "uniswap-v3/price-discovery.mjs",
            "name": "Uniswap V3 Price Server",
            "requiredServerParams": [
                "ETHEREUM_MAINNET_ALCHEMY_HTTP",
                "POLYGON_MAINNET_ALCHEMY_HTTP",
                "ARBITRUM_MAINNET_ALCHEMY_HTTP",
                "OPTIMISM_MAINNET_ALCHEMY_HTTP"
            ],
            "requiredModules": [
                {
                    "name": "ethers",
                    "version": "^6.13.7"
                },
                {
                    "name": "@thanpolas/univ3prices",
                    "version": "^3.0.2"
                }
            ]
        },
        {
            "namespace": "webcareer",
            "file": "web3-career/job-listings.mjs",
            "name": "Web3 Career Job API",
            "requiredServerParams": [
                "WEB3_CAREER_API_TOKEN"
            ],
            "requiredModules": []
        },
        {
            "namespace": "wormholescan",
            "file": "wormholescan/wormholescan.mjs",
            "name": "Wormhole Metrics API",
            "requiredServerParams": [],
            "requiredModules": []
        },
        {
            "namespace": "x402",
            "file": "x402/ping.mjs",
            "name": "x402 Experimental MCP Interface",
            "requiredServerParams": [],
            "requiredModules": []
        }
    ]
}
